test_unit/__init__.py
test_unit/test_codetype.py
test_unit/test_dis.py
test_unit/test_dis27.py
test_unit/test_dis33.py
test_unit/test_dis34.py
test_unit/test_disasm.py
test_unit/test_load.py
test_unit/test_magic.py
test_unit/test_marsh.py
test_unit/test_modules.py
xdis/__init__.py
xdis/__main__.py
xdis/bytecode.py
xdis/cross_dis.py
xdis/cross_types.py
xdis/disasm.py
xdis/instruction.py
xdis/lineoffsets.py
xdis/load.py
xdis/magics.py
xdis/marsh.py
xdis/op_imports.py
xdis/std.py
xdis/unmarshal.py
xdis/util.py
xdis/verify.py
xdis/version.py
xdis/version_info.py
xdis/wordcode.py
xdis/bin/__init__.py
xdis/bin/pydisasm.py
xdis/codetype/__init__.py
xdis/codetype/base.py
xdis/codetype/code13.py
xdis/codetype/code15.py
xdis/codetype/code20.py
xdis/codetype/code30.py
xdis/codetype/code310.py
xdis/codetype/code311.py
xdis/codetype/code38.py
xdis/dropbox/__init__.py
xdis/dropbox/decrypt25.py
xdis/opcodes/__init__.py
xdis/opcodes/base.py
xdis/opcodes/opcode_10.py
xdis/opcodes/opcode_11.py
xdis/opcodes/opcode_12.py
xdis/opcodes/opcode_13.py
xdis/opcodes/opcode_14.py
xdis/opcodes/opcode_15.py
xdis/opcodes/opcode_16.py
xdis/opcodes/opcode_1x.py
xdis/opcodes/opcode_20.py
xdis/opcodes/opcode_21.py
xdis/opcodes/opcode_22.py
xdis/opcodes/opcode_23.py
xdis/opcodes/opcode_24.py
xdis/opcodes/opcode_25.py
xdis/opcodes/opcode_26.py
xdis/opcodes/opcode_26pypy.py
xdis/opcodes/opcode_27.py
xdis/opcodes/opcode_27pypy.py
xdis/opcodes/opcode_2x.py
xdis/opcodes/opcode_30.py
xdis/opcodes/opcode_31.py
xdis/opcodes/opcode_310.py
xdis/opcodes/opcode_310graal.py
xdis/opcodes/opcode_310pypy.py
xdis/opcodes/opcode_311.py
xdis/opcodes/opcode_311pypy.py
xdis/opcodes/opcode_312.py
xdis/opcodes/opcode_312rust.py
xdis/opcodes/opcode_313.py
xdis/opcodes/opcode_314.py
xdis/opcodes/opcode_32.py
xdis/opcodes/opcode_32pypy.py
xdis/opcodes/opcode_33.py
xdis/opcodes/opcode_33pypy.py
xdis/opcodes/opcode_34.py
xdis/opcodes/opcode_35.py
xdis/opcodes/opcode_35pypy.py
xdis/opcodes/opcode_36.py
xdis-6.1.8.dist-info/COPYING
xdis-6.1.8.dist-info/METADATA
xdis-6.1.8.dist-info/WHEEL
xdis-6.1.8.dist-info/entry_points.txt
xdis-6.1.8.dist-info/top_level.txt
xdis-6.1.8.dist-info/zip-safe
xdis-6.1.8.dist-info/RECORD
